ryry/__init__.py
ryry/constant.py
ryry/daemon_base.py
ryry/daemon_manager.py
ryry/main.py
ryry/proxy_manager.py
ryry/ryry_server_socket.py
ryry/ryry_service.py
ryry/ryry_webapi.py
ryry/ryry_widget.py
ryry/server_func.py
ryry/shared_memory.py
ryry/store.py
ryry/task.py
ryry/taskUtils.py
ryry/upload.py
ryry/utils.py
ryry/script_template/__init__.py
ryry/script_template/daemon.py
ryry/script_template/main.py
ryry/script_template/run.py
ryry_cli-6.12.dist-info/LICENSE
ryry_cli-6.12.dist-info/METADATA
ryry_cli-6.12.dist-info/WHEEL
ryry_cli-6.12.dist-info/entry_points.txt
ryry_cli-6.12.dist-info/top_level.txt
ryry_cli-6.12.dist-info/RECORD
