Metadata-Version: 2.1
Name: ryry-cli
Version: 6.12
Summary: ryry tools
Home-page: https://github.com/dalipenMedia
Author: dalipen
Author-email: dalipen01@gmail.com
Classifier: Programming Language :: Python :: 3
Classifier: License :: OSI Approved :: MIT License
Classifier: Operating System :: OS Independent
Requires-Python: >=3.5
License-File: LICENSE
Requires-Dist: requests
Requires-Dist: uuid
Requires-Dist: Image
Requires-Dist: pillow
Requires-Dist: psutil
Requires-Dist: pynvml
Requires-Dist: requests_toolbelt
Requires-Dist: fake_useragent
Requires-Dist: gputil
Requires-Dist: urlparser
Requires-Dist: urllib3
Requires-Dist: portalocker
Requires-Dist: PyYAML
Provides-Extra: with-mecord
Requires-Dist: mecord-cli>=0.7.407; extra == "with-mecord"
